PythonOpencv3JisuanjiShijueMijiChuyiFix1/README.md
PythonOpencv3JisuanjiShijueMijiChuyiFix1/__init__.py
PythonOpencv3JisuanjiShijueMijiChuyiFix1/__main__.py
PythonOpencv3JisuanjiShijueMijiChuyiFix1/file.epub
PythonOpencv3JisuanjiShijueMijiChuyiFix1/index.html
PythonOpencv3JisuanjiShijueMijiChuyiFix1/css/__init__.py
PythonOpencv3JisuanjiShijueMijiChuyiFix1/css/annotations.css
PythonOpencv3JisuanjiShijueMijiChuyiFix1/css/main.css
PythonOpencv3JisuanjiShijueMijiChuyiFix1/css/normalize.css
PythonOpencv3JisuanjiShijueMijiChuyiFix1/css/popup.css
PythonOpencv3JisuanjiShijueMijiChuyiFix1/font/__init__.py
PythonOpencv3JisuanjiShijueMijiChuyiFix1/font/fontello.eot
PythonOpencv3JisuanjiShijueMijiChuyiFix1/font/fontello.svg
PythonOpencv3JisuanjiShijueMijiChuyiFix1/font/fontello.ttf
PythonOpencv3JisuanjiShijueMijiChuyiFix1/font/fontello.woff
PythonOpencv3JisuanjiShijueMijiChuyiFix1/img/__init__.py
PythonOpencv3JisuanjiShijueMijiChuyiFix1/img/annotator-glyph-sprite.png
PythonOpencv3JisuanjiShijueMijiChuyiFix1/img/annotator-icon-sprite.png
PythonOpencv3JisuanjiShijueMijiChuyiFix1/img/apple-touch-icon.png
PythonOpencv3JisuanjiShijueMijiChuyiFix1/img/cancelfullscreen.png
PythonOpencv3JisuanjiShijueMijiChuyiFix1/img/close.png
PythonOpencv3JisuanjiShijueMijiChuyiFix1/img/fullscreen.png
PythonOpencv3JisuanjiShijueMijiChuyiFix1/img/loader.gif
PythonOpencv3JisuanjiShijueMijiChuyiFix1/img/menu-icon.png
PythonOpencv3JisuanjiShijueMijiChuyiFix1/img/save.png
PythonOpencv3JisuanjiShijueMijiChuyiFix1/img/saved.png
PythonOpencv3JisuanjiShijueMijiChuyiFix1/img/settings-s.png
PythonOpencv3JisuanjiShijueMijiChuyiFix1/img/settings.png
PythonOpencv3JisuanjiShijueMijiChuyiFix1/img/star.png
PythonOpencv3JisuanjiShijueMijiChuyiFix1/js/__init__.py
PythonOpencv3JisuanjiShijueMijiChuyiFix1/js/epub.js
PythonOpencv3JisuanjiShijueMijiChuyiFix1/js/epub.min.js
PythonOpencv3JisuanjiShijueMijiChuyiFix1/js/epub.min.map
PythonOpencv3JisuanjiShijueMijiChuyiFix1/js/hooks.min.js
python_opencv3_jisuanji_shijue_miji_chuyi_fix1-2025.3.25.1.dist-info/METADATA
python_opencv3_jisuanji_shijue_miji_chuyi_fix1-2025.3.25.1.dist-info/WHEEL
python_opencv3_jisuanji_shijue_miji_chuyi_fix1-2025.3.25.1.dist-info/entry_points.txt
python_opencv3_jisuanji_shijue_miji_chuyi_fix1-2025.3.25.1.dist-info/top_level.txt
python_opencv3_jisuanji_shijue_miji_chuyi_fix1-2025.3.25.1.dist-info/RECORD
